<annotation>
	<folder></folder>
	<filename>compass_id1746845140133_0_png.rf.012bde34d3b129856300058999d871d1.jpg</filename>
	<path>compass_id1746845140133_0_png.rf.012bde34d3b129856300058999d871d1.jpg</path>
	<source>
		<database>roboflow.com</database>
	</source>
	<size>
		<width>640</width>
		<height>640</height>
		<depth>3</depth>
	</size>
	<segmented>0</segmented>
	<object>
		<name>compass</name>
		<pose>Unspecified</pose>
		<truncated>0</truncated>
		<difficult>0</difficult>
		<occluded>0</occluded>
		<bndbox>
			<xmin>1</xmin>
			<xmax>407</xmax>
			<ymin>1</ymin>
			<ymax>429</ymax>
		</bndbox>
	</object>
	<object>
		<name>compass</name>
		<pose>Unspecified</pose>
		<truncated>0</truncated>
		<difficult>0</difficult>
		<occluded>0</occluded>
		<bndbox>
			<xmin>236</xmin>
			<xmax>641</xmax>
			<ymin>207</ymin>
			<ymax>635</ymax>
		</bndbox>
	</object>
	<metadata>
	</metadata>
</annotation>
